docker_compose_cli/__init__.py
docker_compose_cli/cli.py
docker_compose_cli/templates/Dockerfile
docker_compose_cli/templates/docker-compose.yml
docker_compose_cli-1.0.0.dist-info/LICENSE.md
docker_compose_cli-1.0.0.dist-info/METADATA
docker_compose_cli-1.0.0.dist-info/WHEEL
docker_compose_cli-1.0.0.dist-info/entry_points.txt
docker_compose_cli-1.0.0.dist-info/top_level.txt
docker_compose_cli-1.0.0.dist-info/RECORD
