Metadata-Version: 2.1
Name: docker-compose-cli
Version: 1.0.0
Summary: Docker compose files generator.
Home-page: https://github.com/VoIlAlex/docker-compose-cli
Download-URL: 
Author: voilalex
Author-email: ilya.vouk@gmail.com
License: MIT
Classifier: Development Status :: 1 - Planning
Classifier: Programming Language :: Python :: 3.5
Classifier: Programming Language :: Python :: 3.6
Classifier: Programming Language :: Python :: 3.7
Classifier: Programming Language :: Python :: 3.8
Classifier: Programming Language :: Python :: 3.9
Classifier: Programming Language :: Python :: 3.10
Classifier: Programming Language :: Python :: 3.11
License-File: LICENSE.md
